voter/voter.v
// simple verilog voter

`timescale 1ns / 1ps

module voter (
	input wire a,
	input wire b,
	input wire c,
	output wire v
	);
	
	assign v=a&b|a&c|b&c;
	
endmodule

voter/voter_tb.v
//Testbench for voter

`timescale 1ns / 1ps

module test;

	reg a,b,c;
	wire v;
	
	voter uut(.a(a), .b(b),.c(c),.v(v));
	
	initial begin
	   a=0;
	   b=0;
	   c=0;
	   
	   $dumpfile("voter_tb.vcd");
	   $dumpvars(0, test);
	   
	   #10 c=1;
	   #10 b=1; c=0;
	   #10 c=1;
	   #10 a=1; b=0; c=0;
	   #10 c=1;
	   #10 b=1; c=0;
	   #10 c=1;
	   
	   #20 $finish;
	end
	   
endmodule

voter/voter_tb.vcd
$date
	Tue Jul 26 17:33:33 2022
$end
$version
	Icarus Verilog
$end
$timescale
	1ps
$end
$scope module test $end
$var wire 1 ! v $end
$var reg 1 " a $end
$var reg 1 # b $end
$var reg 1 $ c $end
$scope module uut $end
$var wire 1 " a $end
$var wire 1 # b $end
$var wire 1 $ c $end
$var wire 1 ! v $end
$upscope $end
$upscope $end
$enddefinitions $end
#0
$dumpvars
0$
0#
0"
0!
$end
#10000
1$
#20000
0$
1#
#30000
1!
1$
#40000
0!
0$
0#
1"
#50000
1!
1$
#60000
0$
1#
#70000
1$
